{"stat.useItem.355":5,"stat.horseOneCm":1870577,"stat.craftItem.67":68,"stat.leaveGame":74,"stat.craftItem.339":16,"stat.mineBlock.13":2521,"stat.mineBlock.18":177,"stat.craftItem.331":16,"stat.mineBlock.17":289,"stat.swimOneCm":181853,"stat.useItem.126":13,"stat.mineBlock.19":8,"stat.climbOneCm":375907,"achievement.buildWorkBench":20,"TwilightForest1":1,"lootgames.gol.level3":1,"TwilightForest2":1,"gtpp.start":119,"stat.craftItem.325":1,"achievement.exploreAllBiomes":{"value":0,"progress":["Boneyard","Dead Swamp","Cherry Blossom Grove","rwg_hotDesert","Brushland","Tropical Rainforest","rwg_snowForest","Undergarden","rwg_snowDesert","rwg_riverIce","rwg_riverHot","Mountain","Outback","Phantasmagoric Inferno","Maple Woods","Meadow","rwg_riverWet","Visceral Heap","Boreal Forest","Fungi Forest","Frost Forest","Corrupted Sands","Bayou","Twilight Forest","rwg_riverTemperate","Eerie","Temperate Rainforest","rwg_riverCold","Canyon","rwg_coldForest","Tundra","Mystic Grove","Hell"]},"stat.mineBlock.12":4,"stat.mineBlock.4":2336,"stat.mineBlock.5":2,"stat.mineBlock.3":5236,"stat.mineBlock.1":70215,"stat.mineBlock.6":1,"stat.flyOneCm":5323067,"stat.craftItem.351":6,"stat.craftItem.355":1,"stat.useItem.107":15,"stat.entityKilledBy.enderzoo.FallenKnight":1,"stat.mineBlock.126":11,"stat.mineBlock.129":14,"stat.mineBlock.127":1,"stat.killEntity.Bat":4,"ic2.acquireResin":9,"stat.mineBlock.174":8,"stat.killEntity.Creeper":2,"lootgames.find_dungeon":1,"tconstruct.beginner":9,"stat.useItem.324":1,"achievement.buildSword":2,"achievement.mineWood":352,"stat.useItem.87":361,"stat.useItem.88":6,"achievement.openInventory":7696,"stat.killEntity.enderzoo.ConcussionCreeper":3,"stat.useItem.80":192,"stat.craftItem.44":20,"stat.mineBlock.154":2,"stat.mineBlock.153":23,"stat.mineBlock.159":1376,"stat.entityKilledBy.Creeper":1,"achievement.killEnemy":158,"stat.craftItem.58":3,"stat.deaths":23,"stat.drop":2607,"stat.playOneMinute":5881226,"stat.killEntity.enderzoo.DireWolf":50,"stat.killEntity.Sheep":9,"stat.craftItem.54":70,"stat.killEntity.Zombie":20,"stat.craftItem.306":1,"stat.diveOneCm":97712,"stat.craftItem.307":1,"stat.craftItem.308":1,"stat.craftItem.309":1,"stat.useItem.65":298,"stat.useItem.66":1,"stat.useItem.67":15,"stat.killEntity.Slime":3,"stat.mineBlock.80":3658,"stat.mineBlock.82":242,"stat.mineBlock.87":3708,"stat.mineBlock.89":24,"stat.mineBlock.88":22,"stat.jump":29480,"stat.useItem.401":3,"stat.fallOneCm":847981,"stat.useItem.70":4,"stat.craftItem.171":3,"achievement.killCow":5,"stat.mineBlock.97":28,"stat.useItem.44":97,"stat.craftItem.5":840,"stat.damageTaken":101984,"stat.mineBlock.65":83,"stat.useItem.48":6,"stat.mineBlock.67":15,"stat.useItem.54":49,"stat.mineBlock.79":10,"stat.killEntity.CaveSpider":1,"stat.entityKilledBy.enderzoo.DireWolf":10,"stat.useItem.50":905,"stat.damageDealt":5339,"stat.mineBlock.70":2,"stat.killEntity.Silverfish":1,"stat.killEntity.Cow":9,"dehydrate":3,"stat.killEntity.Pig":2,"stat.useItem.58":7,"stat.mineBlock.78":380,"stat.useItem.397":4,"stat.mineBlock.49":19,"stat.mineBlock.48":17,"stat.useItem.23":2,"stat.useItem.154":1,"stat.walkOneCm":21062316,"stat.useItem.159":10,"stat.playerKills":2,"stat.craftItem.380":2,"stat.blockChiseled":21,"stat.mineBlock.44":76,"stat.mineBlock.58":7,"stat.breakItem.317":1,"stat.mineBlock.103":2,"stat.mineBlock.50":218,"stat.craftItem.126":304,"stat.mineBlock.107":7,"stat.mineBlock.54":55,"stat.useItem.37":8,"stat.useItem.38":2,"stat.killEntity.Skeleton":1,"stat.useItem.258":251,"stat.killEntity.Chicken":4,"stat.craftItem.280":106,"stat.killEntity.Spider":6,"stat.breakItem.307":1,"stat.breakItem.309":1,"stat.mobKills":194,"stat.useItem.380":1,"stat.mineBlock.23":2,"stat.useItem.383":10,"stat.useItem.6":17,"stat.mineBlock.38":1,"stat.mineBlock.37":2,"lootgames.win":1,"stat.useItem.389":3,"stat.useItem.268":6,"stat.useItem.4":5673,"stat.breakItem.300":1,"stat.useItem.3":1551,"stat.useItem.17":8,"stat.useItem.19":6,"stat.mineBlock.30":6,"stat.useItem.13":96,"stat.mineBlock.31":636,"stat.mineBlock.33":1}